LICENSE
README.md
setup.py
payconpy.egg-info/PKG-INFO
payconpy.egg-info/SOURCES.txt
payconpy.egg-info/dependency_links.txt
payconpy.egg-info/requires.txt
payconpy.egg-info/top_level.txt
payconpy/femails/__init__.py
payconpy/femails/femails.py
payconpy/fexceptions/__init__.py
payconpy/fexceptions/exceptions.py
payconpy/ffreesimplegui/__init__.py
payconpy/ffreesimplegui/ffreesimplegui.py
payconpy/fpdf/__init__.py
payconpy/fpdf/utils.py
payconpy/fpdf/compress/__init__.py
payconpy/fpdf/compress/compress.py
payconpy/fpdf/focr/__init__.py
payconpy/fpdf/focr/orc.py
payconpy/fpdf/pdfutils/__init__.py
payconpy/fpdf/pdfutils/pdfutils.py
payconpy/fpython/__init__.py
payconpy/fpython/fpython.py
payconpy/fregex/__init__.py
payconpy/fregex/fregex.py
payconpy/fselenium/__init__.py
payconpy/fselenium/fselenium.py
payconpy/odoo/__init__.py
payconpy/odoo/odoo_xmlrpc.py
payconpy/openai/__init__.py
payconpy/openai/get_cost.py
payconpy/openai/apis/__init__.py
payconpy/openai/apis/apis.py
payconpy/openai/assistants/__init__.py
payconpy/openai/assistants/assistants.py
payconpy/utils/__init__.py
payconpy/utils/utils.py