Metadata-Version: 2.1
Name: payconpy
Version: 5.10.0
Summary: Funções Para Melhorar Desenvolvimento de Robôs com Selenium
Home-page: https://github.com/Paycon-Automacoes/payconpy
Author: Paycon Automações
Author-email: gabriel.souza@paycon.com.br
License: MIT License
Keywords: Funções Para Melhorar Desenvolvimento de Robôs com Selenium
Provides-Extra: openai
Provides-Extra: compress_pdf
License-File: LICENSE
